gbcg3/__init__.py
gbcg3/cgmapping.py
gbcg3/gbcg/__init__.py
gbcg3/gbcg/core.py
gbcg3/gbcg/gbcg.py
gbcg3/gbcg/helpers.py
gbcg3/gbcg/io.py
gbcg3/mapping/__init__.py
gbcg3/mapping/atommaps.py
gbcg3/structure/__init__.py
gbcg3/structure/lammps/__init__.py
gbcg3/structure/lammps/data.py
gbcg3/structure/lammps/helpers.py
gbcg3/structure/lammps/lammps.py
gbcg3/structure/lammps/trajectory.py
gbcg3/structure/lammps/types.py
gbcg3/utils/__init__.py
gbcg3/utils/element_db.py
gbcg3/utils/parser.py
gbcg3-0.1.0.dist-info/METADATA
gbcg3-0.1.0.dist-info/WHEEL
gbcg3-0.1.0.dist-info/RECORD
