Metadata-Version: 2.1
Name: gbcg3
Version: 0.1.0
Summary: 
Author: hodakamori
Author-email: hodaka.mori.office@gmail.com
Requires-Python: >=3.9,<4.0
Classifier: Programming Language :: Python :: 3
Classifier: Programming Language :: Python :: 3.9
Classifier: Programming Language :: Python :: 3.10
Classifier: Programming Language :: Python :: 3.11
Requires-Dist: numpy (>=1.25.0,<2.0.0)
